{
	"Role_Legend": "Jelmagyarázat",
	"Role_Task": "Feladat",
	"Role_StartDate": "Kezdő dátum",
	"Role_Duration": "Időtartam",
	"Role_Completion": "Befejezettség %-ban",
	"Role_Resource": "Erőforrás",
	"Visual_General": "Általános",
	"Visual_GroupTasks": "Csoportos feladatok",
	"Visual_Legend": "Jelmagyarázat",
	"Visual_LegendName": "Jelmagyarázat neve",
	"Visual_LegendColor": "Jelmagyarázat színe",
	"Visual_Show": "Megjelenítés",
	"Visual_Position": "Pozíció",
	"Visual_Position_Top": "Fent",
	"Visual_Position_Bottom": "Lent",
	"Visual_Position_Left": "Balra",
	"Visual_Position_Right": "Jobbra",
	"Visual_Position_TopCenter": "Felül középre",
	"Visual_Position_BottomCenter": "Alul középre",
	"Visual_Position_LeftCenter": "Bal középen",
	"Visual_Position_RightCenter": "Jobb közép",
	"Visual_Title": "Cím",
	"Visual_Color": "Szín",
	"Visual_TextSize": "Szöveg mérete",
	"Visual_Fill": "Kitöltés",
	"Visual_FontSize": "Betűméret",
	"Visual_Width": "Szélesség",
	"Visual_TaskCompletion": "Tevékenység befejezése",
	"Visual_CompletionColor": "Befejezettséget jelölő szín",
	"Visual_DataLabels": "Adatfeliratok",
	"Visual_CategoryLabels": "Kategóriacímkék",
	"Visual_Type": "Típus",
	"Visual_GanttDateType": "Gantt-dátumtípus",
	"Visual_GanttDateType_Day": "Nap",
	"Visual_GanttDateType_Week": "Hét",
	"Visual_GanttDateType_Month": "Hónap",
	"Visual_GanttDateType_Year": "Év"
}